{
    "news": [
        {
            "title": "Khai giang chuong trinh online toeic",
            "description": "Neu ban muon nhanh chong thi de ra truong thi nhanh tay dang ky chuong trinh hoc huu ich",
            "image": "https://...",
            "views": "1234",
            "date": "03/04/2020",
            "content": "<div><p>...</p></div>"
        },
        {
            "title": "Khai giang chuong trinh online toeic 2",
            "description": "Neu ban muon nhanh chong thi de ra truong thi nhanh tay dang ky chuong trinh hoc huu ich",
            "image": "https://...",
            "views": "1234",
            "content": "<div><p>...</p></div>"
        },
        {
            "title": "Khai giang chuong trinh online toeic 3",
            "description": "Neu ban muon nhanh chong thi de ra truong thi nhanh tay dang ky chuong trinh hoc huu ich",
            "image": "https://...",
            "views": "1234",
            "content": "<div><p>...</p></div>"
        },
        {
            "title": "Khai giang chuong trinh online toeic",
            "description": "Neu ban muon nhanh chong thi de ra truong thi nhanh tay dang ky chuong trinh hoc huu ich",
            "image": "https://...",
            "views": "1234",
            "content": "<div><p>...</p></div>"
        },
        
        {
            "title": "Khai giang chuong trinh online toeic 2",
            "description": "Neu ban muon nhanh chong thi de ra truong thi nhanh tay dang ky chuong trinh hoc huu ich",
            "image": "https://...",
            "views": "1234",
            "content": "<div><p>...</p></div>"
        },
        {
            "title": "Khai giang chuong trinh online toeic 3",
            "description": "Neu ban muon nhanh chong thi de ra truong thi nhanh tay dang ky chuong trinh hoc huu ich",
            "image": "https://...",
            "views": "1234",
            "content": "<div><p>...</p></div>"
        }
    ]
}